[{"date":"2026-03-02","round":1,"scoreboard":[{"hero":"アイク","score":3999201217},{"hero":"リョウマ","score":3448770825}]},
{"date":"2026-03-02","round":1,"scoreboard":[{"hero":"エリーゼ","score":3923293310},{"hero":"バルドル","score":4425987376}]},
{"date":"2026-03-02","round":1,"scoreboard":[{"hero":"エーデルガルト","score":4552190244},{"hero":"カムイ","score":4740291301}]},
{"date":"2026-03-02","round":1,"scoreboard":[{"hero":"ベレト","score":5173014235},{"hero":"フレイヤ","score":4170632152}]},
{"date":"2026-03-04","round":2,"scoreboard":[{"hero":"カムイ","score":8357295150},{"hero":"アイク","score":8388677815}]},
{"date":"2026-03-04","round":2,"scoreboard":[{"hero":"ベレト","score":9977431146},{"hero":"バルドル","score":9770016633}]},
{"date":"2026-03-06","round":3,"scoreboard":[{"hero":"ベレト","score":25825613312},{"hero":"アイク","score":26263429296}]}]